{
  "ID": 1829,
  "GUID": "513A4F22-2285-4DC4-9FC6-33A4840F1304",
  "BodyID": 7,
  "BodyName": "Committee on Economic Development",
  "Date": "2002-10-31T13:00:00-05:00",
  "Location": "Committee Room - City Hall",
  "VideoStatus": "Public",
  "AgendaStatusID": 2,
  "AgendaStatusName": "Final",
  "MinutesStatusID": 2,
  "MinutesStatusName": "Final",
  "AgendaFile": "",
  "InSiteURL": "https://nyc.legistar.com/MeetingDetail.aspx?LEGID=1829&GID=61&G=2FD004F1-D85B-4588-A648-0A736C77D6E3",
  "Items": [
    {
      "ID": 135776,
      "GUID": "29D86481-8143-4D7B-A0EB-FBABC79F64B1",
      "Title": "Resolution calling for United Cerebral Palsy of New York City to negotiate in good faith and finalize a contract with the United Federation of Teachers.",
      "AgendaSequence": 1,
      "MinutesSequence": 3,
      "Version": "*",
      "ActionID": 54,
      "ActionName": "Hearing Held by Committee",
      "MatterID": 26254,
      "MatterFile": "Res 0470-2002",
      "MatterName": "United Cerebral Palsy of NYC to negotiate in good faith and finalize a contract with the United Federation of Teachers.",
      "MatterType": "Resolution",
      "MatterStatus": "Filed",
      "LastModified": "2015-08-25T15:58:59.527Z"
    },
    {
      "ID": 135852,
      "GUID": "39DDA1CD-B817-4E97-993B-4FAF5DF3BAEA",
      "Title": "Resolution calling for United Cerebral Palsy of New York City to negotiate in good faith and finalize a contract with the United Federation of Teachers.",
      "AgendaSequence": 0,
      "MinutesSequence": 4,
      "Version": "*",
      "ActionID": 17,
      "ActionName": "Laid Over by Committee",
      "MatterID": 26254,
      "MatterFile": "Res 0470-2002",
      "MatterName": "United Cerebral Palsy of NYC to negotiate in good faith and finalize a contract with the United Federation of Teachers.",
      "MatterType": "Resolution",
      "MatterStatus": "Filed",
      "LastModified": "2015-08-25T15:58:59.527Z"
    },
    {
      "ID": 135853,
      "GUID": "1C4EE2F1-19DA-47B7-92AF-D965E2DE6234",
      "Title": "Roll Call",
      "AgendaSequence": 0,
      "MinutesSequence": 1,
      "Version": "",
      "RollCallFlag": 1,
      "RollCall": [
        {
          "ID": 5280,
          "Slug": "james-sanders-jr",
          "FullName": "James Sanders, Jr.",
          "ValueID": 13,
          "Value": "Present",
          "Sort": 10
        },
        {
          "ID": 5256,
          "Slug": "diana-reyna",
          "FullName": "Diana Reyna",
          "ValueID": 13,
          "Value": "Present",
          "Sort": 30
        },
        {
          "ID": 5287,
          "Slug": "yvette-d-clarke",
          "FullName": "Yvette D. Clarke",
          "ValueID": 13,
          "Value": "Present",
          "Sort": 40
        },
        {
          "ID": 5285,
          "Slug": "erik-martin-dilan",
          "FullName": "Erik Martin Dilan",
          "ValueID": 13,
          "Value": "Present",
          "Sort": 50
        },
        {
          "ID": 5258,
          "Slug": "alan-j-gerson",
          "FullName": "Alan J. Gerson",
          "ValueID": 16,
          "Value": "Absent",
          "Sort": 60
        },
        {
          "ID": 5275,
          "Slug": "eric-n-gioia",
          "FullName": "Eric N. Gioia",
          "ValueID": 13,
          "Value": "Present",
          "Sort": 70
        },
        {
          "ID": 5292,
          "Slug": "domenic-m-recchia-jr",
          "FullName": "Domenic M. Recchia, Jr.",
          "ValueID": 13,
          "Value": "Present",
          "Sort": 80
        },
        {
          "ID": 436,
          "Slug": "james-s-oddo",
          "FullName": "James S. Oddo",
          "ValueID": 13,
          "Value": "Present",
          "Sort": 90
        }
      ],
      "LastModified": "2015-08-25T15:58:59.527Z"
    },
    {
      "ID": 135962,
      "GUID": "7404FCBE-511A-4AFB-ADAD-E316F988D61B",
      "Title": "",
      "AgendaSequence": 0,
      "MinutesSequence": 2,
      "Version": "",
      "MinutesNote": "Other Council Members Attending:  Quinn",
      "LastModified": "2015-08-25T15:58:59.527Z"
    }
  ],
  "AgendaLastPublished": "2009-10-22T15:49:29.74Z",
  "MinutesLastPublished": "2010-02-23T16:45:38.62Z",
  "LastModified": "2015-08-25T15:57:12.06Z"
}
