{
  "ID": 1904,
  "GUID": "DD465222-3C77-4FF5-8357-C33ED260AABB",
  "BodyID": 20,
  "BodyName": "Committee on Rules, Privileges and Elections",
  "Date": "2002-11-25T12:00:00-05:00",
  "Location": "Council Chambers - City Hall",
  "VideoStatus": "Public",
  "AgendaStatusID": 2,
  "AgendaStatusName": "Final",
  "MinutesStatusID": 2,
  "MinutesStatusName": "Final",
  "AgendaFile": "",
  "InSiteURL": "https://nyc.legistar.com/MeetingDetail.aspx?LEGID=1904&GID=61&G=2FD004F1-D85B-4588-A648-0A736C77D6E3",
  "Items": [
    {
      "ID": 136689,
      "GUID": "00FC5D43-2BB6-420C-B8DE-751F0CB452A4",
      "Title": "Resolution approving Membership Changes to Certain Standing Committees",
      "AgendaSequence": 1,
      "MinutesSequence": 2,
      "Version": "*",
      "AgendaNote": "Preconsidered",
      "ActionID": 15,
      "ActionName": "Hearing on P-C Item by Comm",
      "MatterID": 26662,
      "MatterFile": "Res 0602-2002",
      "MatterName": "Membership Changes to Certain Standing Committees",
      "MatterType": "Resolution",
      "MatterStatus": "Adopted",
      "LastModified": "2015-08-25T15:58:59.527Z"
    },
    {
      "ID": 136762,
      "GUID": "40EE57C2-3C30-46BD-93CD-0D0A741F9550",
      "Title": "Resolution approving Membership Changes to Certain Standing Committees",
      "AgendaSequence": 0,
      "MinutesSequence": 3,
      "Version": "*",
      "ActionID": 25,
      "ActionName": "P-C Item Approved by Comm",
      "PassedFlag": 1,
      "PassedFlagName": "Pass",
      "MatterID": 26662,
      "MatterFile": "Res 0602-2002",
      "MatterName": "Membership Changes to Certain Standing Committees",
      "MatterType": "Resolution",
      "MatterStatus": "Adopted",
      "LastModified": "2015-08-25T15:58:59.527Z"
    },
    {
      "ID": 136763,
      "GUID": "262FB024-5BDF-4288-80EF-734AE8A9B3EB",
      "Title": "Roll Call",
      "AgendaSequence": 0,
      "MinutesSequence": 1,
      "Version": "",
      "RollCallFlag": 1,
      "RollCall": [
        {
          "ID": 5276,
          "Slug": "leroy-g-comrie-jr",
          "FullName": "Leroy G. Comrie, Jr.",
          "ValueID": 13,
          "Value": "Present",
          "Sort": 10
        },
        {
          "ID": 430,
          "Slug": "bill-perkins",
          "FullName": "Bill Perkins",
          "ValueID": 13,
          "Value": "Present",
          "Sort": 20
        },
        {
          "ID": 431,
          "Slug": "madeline-t-provenzano",
          "FullName": "Madeline T. Provenzano",
          "ValueID": 13,
          "Value": "Present",
          "Sort": 30
        },
        {
          "ID": 434,
          "Slug": "christine-c-quinn",
          "FullName": "Christine C. Quinn",
          "ValueID": 13,
          "Value": "Present",
          "Sort": 40
        },
        {
          "ID": 5244,
          "Slug": "joel-rivera",
          "FullName": "Joel Rivera",
          "ValueID": 13,
          "Value": "Present",
          "Sort": 50
        },
        {
          "ID": 5268,
          "Slug": "tony-avella",
          "FullName": "Tony Avella",
          "ValueID": 13,
          "Value": "Present",
          "Sort": 60
        },
        {
          "ID": 5264,
          "Slug": "maria-baez",
          "FullName": "Maria Baez",
          "ValueID": 13,
          "Value": "Present",
          "Sort": 70
        },
        {
          "ID": 5287,
          "Slug": "yvette-d-clarke",
          "FullName": "Yvette D. Clarke",
          "ValueID": 13,
          "Value": "Present",
          "Sort": 80
        },
        {
          "ID": 5291,
          "Slug": "lewis-a-fidler",
          "FullName": "Lewis A. Fidler",
          "ValueID": 13,
          "Value": "Present",
          "Sort": 90
        },
        {
          "ID": 5278,
          "Slug": "melinda-r-katz",
          "FullName": "Melinda R. Katz",
          "ValueID": 13,
          "Value": "Present",
          "Sort": 100
        },
        {
          "ID": 5272,
          "Slug": "david-i-weprin",
          "FullName": "David I. Weprin",
          "ValueID": 13,
          "Value": "Present",
          "Sort": 110
        },
        {
          "ID": 436,
          "Slug": "james-s-oddo",
          "FullName": "James S. Oddo",
          "ValueID": 13,
          "Value": "Present",
          "Sort": 120
        },
        {
          "ID": 422,
          "Slug": "gifford-miller",
          "FullName": "Gifford Miller",
          "ValueID": 13,
          "Value": "Present",
          "Sort": 130
        }
      ],
      "LastModified": "2015-08-25T15:58:59.527Z"
    }
  ],
  "AgendaLastPublished": "2009-10-22T15:37:46.613Z",
  "MinutesLastPublished": "2010-02-23T16:13:06.453Z",
  "LastModified": "2015-08-25T15:57:12.06Z"
}
