{
  "ID": 7799,
  "GUID": "96199E4E-8A08-4B9D-8F07-1C88A73AB175",
  "Slug": "eric-dinowitz",
  "IsActive": true,
  "Email": "District11@council.nyc.gov",
  "FullName": "Eric Dinowitz",
  "FirstName": "Eric",
  "LastName": "Dinowitz",
  "WWW": "https://council.nyc.gov/district-11/",
  "LastModified": "2021-04-19T16:53:18.667Z",
  "OfficeRecords": [
    {
      "ID": 4436,
      "GUID": "4E587EB6-5F0C-4EFB-88C0-22C2AA9E0483",
      "BodyID": 1,
      "BodyName": "City Council",
      "MemberType": "PRIMARY COUNCIL MEMBERS",
      "Title": "Council Member",
      "MemberTypeID": 3,
      "FullName": "Eric Dinowitz",
      "PersonID": 7799,
      "Start": "2021-04-15T00:00:00Z",
      "End": "2021-12-31T00:00:00Z",
      "LastModified": "2021-04-19T17:05:11.02Z"
    },
    {
      "ID": 4438,
      "GUID": "459246D9-FC23-4934-B14C-5AAA1B8CDA30",
      "BodyID": 3,
      "BodyName": "Committee on Aging",
      "MemberType": "PRIMARY COUNCIL MEMBERS",
      "Title": "Committee Member",
      "MemberTypeID": 3,
      "FullName": "Eric Dinowitz",
      "PersonID": 7799,
      "Start": "2021-04-22T00:00:00Z",
      "End": "2021-12-31T00:00:00Z",
      "LastModified": "2021-04-22T16:01:03.987Z"
    },
    {
      "ID": 4439,
      "GUID": "5FD42A26-B4A2-48EE-8244-AB761F0F4A56",
      "BodyID": 4,
      "BodyName": "Committee on Civil Service and Labor",
      "MemberType": "PRIMARY COUNCIL MEMBERS",
      "Title": "Committee Member",
      "MemberTypeID": 3,
      "FullName": "Eric Dinowitz",
      "PersonID": 7799,
      "Start": "2021-04-22T00:00:00Z",
      "End": "2021-12-31T00:00:00Z",
      "LastModified": "2021-04-22T16:04:03.553Z"
    },
    {
      "ID": 4440,
      "GUID": "3EAB6A20-EF63-4905-BEFC-58643EDDAF74",
      "BodyID": 5236,
      "BodyName": "Committee on Consumer Affairs and Business Licensing",
      "MemberType": "PRIMARY COUNCIL MEMBERS",
      "Title": "Committee Member",
      "MemberTypeID": 3,
      "FullName": "Eric Dinowitz",
      "PersonID": 7799,
      "Start": "2021-04-22T00:00:00Z",
      "End": "2021-05-12T00:00:00Z",
      "LastModified": "2021-04-22T16:08:12.36Z"
    },
    {
      "ID": 4441,
      "GUID": "17388BF5-F62B-4D46-A626-BAECBCAE88A9",
      "BodyID": 9,
      "BodyName": "Committee on Education",
      "MemberType": "PRIMARY COUNCIL MEMBERS",
      "Title": "Committee Member",
      "MemberTypeID": 3,
      "FullName": "Eric Dinowitz",
      "PersonID": 7799,
      "Start": "2021-04-23T00:00:00Z",
      "End": "2021-12-31T00:00:00Z",
      "LastModified": "2021-04-22T16:12:20.74Z"
    },
    {
      "ID": 4450,
      "GUID": "DB055851-1DA3-4594-83E6-C706E8C58668",
      "BodyID": 5243,
      "BodyName": "Committee on Mental Health, Disabilities and Addiction",
      "MemberType": "PRIMARY COUNCIL MEMBERS",
      "Title": "Committee Member",
      "MemberTypeID": 3,
      "FullName": "Eric Dinowitz",
      "PersonID": 7799,
      "Start": "2021-04-22T00:00:00Z",
      "End": "2021-12-31T00:00:00Z",
      "LastModified": "2021-04-22T16:34:39.78Z"
    },
    {
      "ID": 4451,
      "GUID": "06D5C0B5-DD83-4631-9ADD-B85A5916C612",
      "BodyID": 5107,
      "BodyName": "Committee on Oversight and Investigations",
      "MemberType": "PRIMARY COUNCIL MEMBERS",
      "Title": "Committee Member",
      "MemberTypeID": 3,
      "FullName": "Eric Dinowitz",
      "PersonID": 7799,
      "Start": "2021-04-22T00:00:00Z",
      "End": "2021-12-31T00:00:00Z",
      "LastModified": "2021-04-22T16:36:34.467Z"
    },
    {
      "ID": 4452,
      "GUID": "EBED91A0-8319-46CA-AF3F-F4580B336FAB",
      "BodyID": 5106,
      "BodyName": "Committee on Parks and Recreation",
      "MemberType": "PRIMARY COUNCIL MEMBERS",
      "Title": "Committee Member",
      "MemberTypeID": 3,
      "FullName": "Eric Dinowitz",
      "PersonID": 7799,
      "Start": "2021-04-22T00:00:00Z",
      "End": "2021-12-31T00:00:00Z",
      "LastModified": "2021-04-22T16:39:01.157Z"
    },
    {
      "ID": 4455,
      "GUID": "7A286478-A049-423E-B493-554C1F98767E",
      "BodyID": 5120,
      "BodyName": "Committee on Small Business",
      "MemberType": "PRIMARY COUNCIL MEMBERS",
      "Title": "Committee Member",
      "MemberTypeID": 3,
      "FullName": "Eric Dinowitz",
      "PersonID": 7799,
      "Start": "2021-04-22T00:00:00Z",
      "End": "2021-12-31T00:00:00Z",
      "LastModified": "2021-04-22T16:46:31.44Z"
    },
    {
      "ID": 4459,
      "GUID": "DB1E9238-2582-4DCA-8318-7A0820A4A11B",
      "BodyID": 5257,
      "BodyName": "Democratic Conference of the Council of the City of New York ",
      "MemberType": "PRIMARY COUNCIL MEMBERS",
      "Title": "Council Member",
      "MemberTypeID": 3,
      "FullName": "Eric Dinowitz",
      "PersonID": 7799,
      "Start": "2021-04-15T00:00:00Z",
      "End": "2021-12-31T00:00:00Z",
      "LastModified": "2021-04-28T13:48:16.853Z"
    },
    {
      "ID": 4463,
      "GUID": "50B8A5A8-52C2-40B7-B485-B4170279A8F2",
      "BodyID": 5122,
      "BodyName": "Committee on Veterans",
      "MemberType": "PRIMARY COUNCIL MEMBERS",
      "Title": "CHAIRPERSON",
      "MemberTypeID": 3,
      "FullName": "Eric Dinowitz",
      "PersonID": 7799,
      "Start": "2021-05-12T00:00:00Z",
      "End": "2021-12-31T00:00:00Z",
      "LastModified": "2021-05-12T13:06:22.027Z"
    },
    {
      "ID": 4486,
      "GUID": "6E5BF2C3-1837-4486-A1F5-8E46CBC12EE3",
      "BodyID": 1,
      "BodyName": "City Council",
      "MemberType": "PRIMARY COUNCIL MEMBERS",
      "Title": "Council Member",
      "MemberTypeID": 3,
      "FullName": "Eric Dinowitz",
      "PersonID": 7799,
      "Start": "2022-01-01T00:00:00Z",
      "End": "2023-12-31T00:00:00Z",
      "LastModified": "2021-11-03T17:15:56.09Z"
    },
    {
      "ID": 4547,
      "GUID": "83C4A315-E7FA-431B-B8C8-B521553AEDBF",
      "BodyID": 5257,
      "BodyName": "Democratic Conference of the Council of the City of New York ",
      "MemberType": "PRIMARY COUNCIL MEMBERS",
      "Title": "Council Member",
      "MemberTypeID": 3,
      "FullName": "Eric Dinowitz",
      "PersonID": 7799,
      "Start": "2022-01-01T00:00:00Z",
      "End": "2023-12-31T00:00:00Z",
      "LastModified": "2021-12-15T21:29:26.717Z"
    },
    {
      "ID": 4600,
      "GUID": "0B5057EE-053B-44E3-B45E-7F6E16B54201",
      "BodyID": 3,
      "BodyName": "Committee on Aging",
      "MemberType": "PRIMARY COUNCIL MEMBERS",
      "Title": "Committee Member",
      "MemberTypeID": 3,
      "FullName": "Eric Dinowitz",
      "PersonID": 7799,
      "Start": "2022-01-20T00:00:00Z",
      "End": "2023-12-31T00:00:00Z",
      "LastModified": "2022-01-20T13:35:11.337Z"
    },
    {
      "ID": 4626,
      "GUID": "1363B077-785D-41DF-A2E6-EB497C463646",
      "BodyID": 4,
      "BodyName": "Committee on Civil Service and Labor",
      "MemberType": "PRIMARY COUNCIL MEMBERS",
      "Title": "Committee Member",
      "MemberTypeID": 3,
      "FullName": "Eric Dinowitz",
      "PersonID": 7799,
      "Start": "2022-01-20T00:00:00Z",
      "End": "2023-12-31T00:00:00Z",
      "LastModified": "2022-01-20T15:43:32.27Z"
    },
    {
      "ID": 4659,
      "GUID": "FF5C452D-9EEB-4141-AE5C-4CB095A2C390",
      "BodyID": 5105,
      "BodyName": "Committee on Cultural Affairs, Libraries and International Intergroup Relations",
      "MemberType": "PRIMARY COUNCIL MEMBERS",
      "Title": "Committee Member",
      "MemberTypeID": 3,
      "FullName": "Eric Dinowitz",
      "PersonID": 7799,
      "Start": "2022-01-20T00:00:00Z",
      "End": "2023-12-31T00:00:00Z",
      "LastModified": "2022-01-20T18:59:24.3Z"
    },
    {
      "ID": 4677,
      "GUID": "5DCD708B-13BD-42F2-B418-C7B6343F3926",
      "BodyID": 9,
      "BodyName": "Committee on Education",
      "MemberType": "PRIMARY COUNCIL MEMBERS",
      "Title": "Committee Member",
      "MemberTypeID": 3,
      "FullName": "Eric Dinowitz",
      "PersonID": 7799,
      "Start": "2022-01-20T00:00:00Z",
      "End": "2023-12-31T00:00:00Z",
      "LastModified": "2022-01-20T19:36:43.953Z"
    },
    {
      "ID": 4732,
      "GUID": "701BEB50-71A1-4E17-8945-63FA2CFBF7D9",
      "BodyID": 13,
      "BodyName": "Committee on Governmental Operations",
      "MemberType": "PRIMARY COUNCIL MEMBERS",
      "Title": "Committee Member",
      "MemberTypeID": 3,
      "FullName": "Eric Dinowitz",
      "PersonID": 7799,
      "Start": "2022-01-20T00:00:00Z",
      "End": "2022-02-24T00:00:00Z",
      "LastModified": "2022-01-20T22:29:55.27Z"
    },
    {
      "ID": 4744,
      "GUID": "A75BE1FA-30C4-42A2-B390-B297B9E41E05",
      "BodyID": 15,
      "BodyName": "Committee on Higher Education",
      "MemberType": "CHAIR",
      "Title": "CHAIRPERSON",
      "MemberTypeID": 1,
      "FullName": "Eric Dinowitz",
      "PersonID": 7799,
      "Start": "2022-01-20T00:00:00Z",
      "End": "2023-12-31T00:00:00Z",
      "LastModified": "2022-01-20T22:43:34.807Z"
    },
    {
      "ID": 4760,
      "GUID": "F8C9B72C-0963-4C84-B3E1-7BF22FE1037F",
      "BodyID": 16,
      "BodyName": "Committee on Housing and Buildings",
      "MemberType": "PRIMARY COUNCIL MEMBERS",
      "Title": "Committee Member",
      "MemberTypeID": 3,
      "FullName": "Eric Dinowitz",
      "PersonID": 7799,
      "Start": "2022-01-20T00:00:00Z",
      "End": "2023-12-31T00:00:00Z",
      "LastModified": "2022-01-20T23:15:58.74Z"
    },
    {
      "ID": 4806,
      "GUID": "18EB0496-1DC1-4114-9536-A752A8FDCC2E",
      "BodyID": 5106,
      "BodyName": "Committee on Parks and Recreation",
      "MemberType": "PRIMARY COUNCIL MEMBERS",
      "Title": "Committee Member",
      "MemberTypeID": 3,
      "FullName": "Eric Dinowitz",
      "PersonID": 7799,
      "Start": "2022-01-20T00:00:00Z",
      "End": "2023-12-31T00:00:00Z",
      "LastModified": "2022-01-21T00:12:38.563Z"
    },
    {
      "ID": 4865,
      "GUID": "FAABBABE-462F-4251-A663-E93034DAF64C",
      "BodyID": 21,
      "BodyName": "Committee on Standards and Ethics",
      "MemberType": "PRIMARY COUNCIL MEMBERS",
      "Title": "Committee Member",
      "MemberTypeID": 3,
      "FullName": "Eric Dinowitz",
      "PersonID": 7799,
      "Start": "2022-01-20T00:00:00Z",
      "End": "2023-12-31T00:00:00Z",
      "LastModified": "2022-01-21T01:40:56.07Z"
    },
    {
      "ID": 4895,
      "GUID": "C13006A5-25FE-4BC4-8BEF-90FD88790BC2",
      "BodyID": 5122,
      "BodyName": "Committee on Veterans",
      "MemberType": "PRIMARY COUNCIL MEMBERS",
      "Title": "Committee Member",
      "MemberTypeID": 3,
      "FullName": "Eric Dinowitz",
      "PersonID": 7799,
      "Start": "2022-01-20T00:00:00Z",
      "End": "2022-02-24T00:00:00Z",
      "LastModified": "2022-01-21T02:14:26.88Z"
    },
    {
      "ID": 4928,
      "GUID": "298CCC94-6EF3-4E36-9044-FE70AF91384F",
      "BodyID": 5272,
      "BodyName": "Subcommittee on Senior Centers and Food Insecurity",
      "MemberType": "PRIMARY COUNCIL MEMBERS",
      "Title": "Committee Member",
      "MemberTypeID": 3,
      "FullName": "Eric Dinowitz",
      "PersonID": 7799,
      "Start": "2022-01-20T00:00:00Z",
      "End": "2022-02-24T00:00:00Z",
      "LastModified": "2022-01-21T02:51:12.05Z"
    },
    {
      "ID": 4954,
      "GUID": "513BB555-1955-4123-8C00-69494FA6E43C",
      "BodyID": 5283,
      "BodyName": "Caucus - Jewish Caucus",
      "MemberType": "CHAIR",
      "Title": "CHAIRPERSON",
      "MemberTypeID": 1,
      "FullName": "Eric Dinowitz",
      "PersonID": 7799,
      "Start": "2022-01-01T00:00:00Z",
      "End": "2023-12-31T00:00:00Z",
      "LastModified": "2022-04-05T16:25:17.55Z"
    },
    {
      "ID": 5017,
      "GUID": "194C18DC-A7AB-4F57-B4E4-5856479DD58A",
      "BodyID": 5285,
      "BodyName": "Caucus - Progressive Caucus",
      "MemberType": "PRIMARY COUNCIL MEMBERS",
      "Title": "Council Member",
      "MemberTypeID": 3,
      "FullName": "Eric Dinowitz",
      "PersonID": 7799,
      "Start": "2022-01-01T00:00:00Z",
      "End": "2023-12-31T00:00:00Z",
      "LastModified": "2022-04-06T18:21:01.19Z"
    },
    {
      "ID": 5084,
      "GUID": "7AD8F310-2543-476E-9941-101186BC29B8",
      "BodyID": 5224,
      "BodyName": "Committee of the Whole",
      "MemberType": "PRIMARY COUNCIL MEMBERS",
      "Title": "Committee Member",
      "MemberTypeID": 3,
      "FullName": "Eric Dinowitz",
      "PersonID": 7799,
      "Start": "2022-01-05T00:00:00Z",
      "End": "2023-12-31T00:00:00Z",
      "LastModified": "2022-11-14T21:28:40.137Z"
    },
    {
      "ID": 5202,
      "GUID": "52C8A12E-3E96-432F-B981-6AA96DC9EE0B",
      "BodyID": 5292,
      "BodyName": "Bronx Delegation of the New York City Council",
      "MemberType": "CHAIR",
      "Title": "Co-Chair",
      "MemberTypeID": 1,
      "FullName": "Eric Dinowitz",
      "PersonID": 7799,
      "Start": "2022-01-01T00:00:00Z",
      "End": "2023-12-31T00:00:00Z",
      "LastModified": "2023-03-20T13:07:48.653Z"
    },
    {
      "ID": 5224,
      "GUID": "A29D807D-5623-46F6-8C47-56EAD36D46BC",
      "BodyID": 1,
      "BodyName": "City Council",
      "MemberType": "PRIMARY COUNCIL MEMBERS",
      "Title": "Council Member",
      "MemberTypeID": 3,
      "FullName": "Eric Dinowitz",
      "PersonID": 7799,
      "Start": "2024-01-01T00:00:00Z",
      "End": "2025-12-31T00:00:00Z",
      "LastModified": "2023-11-08T18:29:54.963Z"
    },
    {
      "ID": 5279,
      "GUID": "319E102F-9ADD-4AD4-A105-0CA085E1F8F4",
      "BodyID": 5257,
      "BodyName": "Democratic Conference of the Council of the City of New York ",
      "MemberType": "PRIMARY COUNCIL MEMBERS",
      "Title": "Council Member",
      "MemberTypeID": 3,
      "FullName": "Eric Dinowitz",
      "PersonID": 7799,
      "Start": "2024-01-01T00:00:00Z",
      "End": "2025-12-31T00:00:00Z",
      "LastModified": "2024-01-01T15:48:46.83Z"
    },
    {
      "ID": 5368,
      "GUID": "D90AFADB-2A23-414C-A7CD-6FE0E09088F9",
      "BodyID": 5272,
      "BodyName": "Subcommittee on Senior Centers and Food Insecurity",
      "MemberType": "PRIMARY COUNCIL MEMBERS",
      "Title": "Committee Member",
      "MemberTypeID": 3,
      "FullName": "Eric Dinowitz",
      "PersonID": 7799,
      "Start": "2024-01-18T00:00:00Z",
      "End": "2025-12-31T00:00:00Z",
      "LastModified": "2024-01-18T18:03:07.74Z"
    },
    {
      "ID": 5378,
      "GUID": "5EEFDE97-30B0-4890-A629-06DDC16D3F00",
      "BodyID": 4,
      "BodyName": "Committee on Civil Service and Labor",
      "MemberType": "PRIMARY COUNCIL MEMBERS",
      "Title": "Committee Member",
      "MemberTypeID": 3,
      "FullName": "Eric Dinowitz",
      "PersonID": 7799,
      "Start": "2024-01-18T00:00:00Z",
      "End": "2025-12-31T00:00:00Z",
      "LastModified": "2024-01-18T18:13:24.007Z"
    }
  ],
  "Start": "2021-04-15T00:00:00Z",
  "End": "2025-12-31T00:00:00Z",
  "DistrictOffice": {
    "Address": "277 West 231st Street",
    "City": "Bronx",
    "State": "NY",
    "Zip": "10463"
  },
  "LegislativeOffice": {
    "Address": "250 Broadway, Suite 1868",
    "City": "New York",
    "State": "NY",
    "Zip": "10007"
  }
}
