{
  "ID": 16770,
  "GUID": "830BDD0B-AF19-4C0A-8E6B-FB0474B4DCEC",
  "BodyID": 5237,
  "BodyName": "Committee on Criminal Justice",
  "Date": "2018-12-03T10:00:00-05:00",
  "Location": "Council Chambers - City Hall",
  "VideoStatus": "Public",
  "AgendaStatusID": 2,
  "AgendaStatusName": "Final",
  "MinutesStatusID": 2,
  "MinutesStatusName": "Final",
  "AgendaFile": "http://nyc.legistar1.com/nyc/meetings/2018/12/16770_A_Committee_on_Criminal_Justice_18-12-03_Committee_Green_Sheet.pdf",
  "MinutesFile": "http://nyc.legistar1.com/nyc/meetings/2018/12/16770_M_Committee_on_Criminal_Justice_18-12-03_Meeting_Minutes.pdf",
  "Comment": "Jointly with the Committee on Justice System",
  "VideoPath": "https://councilnyc.viebit.com/vod/?s=true&v=NYCC-PV-CH-CHA_181203-100838.mp4",
  "Media": "https://councilnyc.viebit.com/vod/?s=true&v=NYCC-PV-CH-CHA_181203-100838.mp4",
  "InSiteURL": "https://nyc.legistar.com/MeetingDetail.aspx?LEGID=16770&GID=61&G=2FD004F1-D85B-4588-A648-0A736C77D6E3",
  "Items": [
    {
      "ID": 343653,
      "GUID": "56FFAA04-C730-41DB-BD1F-B79FC228AD04",
      "Title": "Oversight - Why does the City make it so hard to post bail?",
      "AgendaSequence": 1,
      "MinutesSequence": 3,
      "Version": "*",
      "ActionID": 54,
      "ActionName": "Hearing Held by Committee",
      "ActionText": "This Oversight was Hearing Held by Committee",
      "MatterID": 61827,
      "MatterFile": "T2018-3185",
      "MatterName": "Oversight - Why does the City make it so hard to post bail?",
      "MatterType": "Oversight",
      "MatterStatus": "Filed",
      "LastModified": "2018-12-03T18:11:07.58Z"
    },
    {
      "ID": 343654,
      "GUID": "09D18AA0-2088-49A8-86AF-29B8786D9135",
      "Title": "Jointly with the Committee on Justice System",
      "AgendaSequence": 4,
      "MinutesSequence": 9,
      "Version": "",
      "LastModified": "2018-12-03T18:10:26.737Z"
    },
    {
      "ID": 343655,
      "GUID": "FECE48CF-A80E-4580-9AB3-51B10484847A",
      "Title": "A Local Law to amend the administrative code of the city of New York, in relation to requiring the department of correction to notify incarcerated individuals and their legal representatives when an incarcerated individual is held solely due to a bail amount of less than $10",
      "AgendaSequence": 2,
      "MinutesSequence": 5,
      "Version": "*",
      "ActionID": 54,
      "ActionName": "Hearing Held by Committee",
      "ActionText": "This Introduction was Hearing Held by Committee",
      "MatterID": 60760,
      "MatterFile": "Int 0944-2018",
      "MatterName": "Requiring the dept of correction to notify inmates, defense attorneys, and court personnel when an inmate is detained solely on a bail amount of one dollar.",
      "MatterType": "Introduction",
      "MatterStatus": "Enacted",
      "LastModified": "2018-12-03T18:11:15.353Z"
    },
    {
      "ID": 343656,
      "GUID": "1A1B9E67-75A3-440E-AEDE-165AC27D4890",
      "Title": "A Local Law to amend the administrative code of the city of New York, in relation to removing fees associated with bail payments",
      "AgendaSequence": 3,
      "MinutesSequence": 7,
      "Version": "*",
      "ActionID": 54,
      "ActionName": "Hearing Held by Committee",
      "ActionText": "This Introduction was Hearing Held by Committee",
      "MatterID": 61583,
      "MatterFile": "Int 1199-2018",
      "MatterName": "Removing fees associated with credit card bail payments and in relation to allowing online bail payment to be made by direct deposit and electronic check.",
      "MatterType": "Introduction",
      "MatterStatus": "Enacted",
      "LastModified": "2018-12-03T18:11:23.943Z"
    },
    {
      "ID": 343817,
      "GUID": "35DCCCDF-2212-4668-B45E-E1EC85B0B53C",
      "Title": "Roll Call",
      "AgendaSequence": 0,
      "MinutesSequence": 1,
      "Version": "",
      "RollCallFlag": 1,
      "RollCall": [
        {
          "ID": 7741,
          "Slug": "keith-powers",
          "FullName": "Keith Powers",
          "ValueID": 13,
          "Value": "Present",
          "Sort": 10
        },
        {
          "ID": 7747,
          "Slug": "alicka-ampry-samuel",
          "FullName": "Alicka Ampry-Samuel",
          "ValueID": 13,
          "Value": "Present",
          "Sort": 20
        },
        {
          "ID": 7746,
          "Slug": "robert-f-holden",
          "FullName": "Robert F. Holden",
          "ValueID": 13,
          "Value": "Present",
          "Sort": 30
        },
        {
          "ID": 7633,
          "Slug": "rory-i-lancman",
          "FullName": "Rory I. Lancman",
          "ValueID": 13,
          "Value": "Present",
          "Sort": 40
        },
        {
          "ID": 7740,
          "Slug": "carlina-rivera",
          "FullName": "Carlina Rivera",
          "ValueID": 13,
          "Value": "Present",
          "Sort": 50
        }
      ],
      "LastModified": "2018-12-03T20:09:08.953Z"
    },
    {
      "ID": 343818,
      "GUID": "18DDC6E6-CE13-4D94-BB1B-D9208EBDA714",
      "Title": "",
      "AgendaSequence": 0,
      "MinutesSequence": 2,
      "Version": "",
      "MinutesNote": "Other Council Members Attending: Cohen, Maisel and Rose",
      "LastModified": "2018-12-03T18:11:03.96Z"
    },
    {
      "ID": 343819,
      "GUID": "ABC09B1A-D313-445F-B7F8-B11D16C1F6C2",
      "Title": "Oversight - Why does the City make it so hard to post bail?",
      "AgendaSequence": 0,
      "MinutesSequence": 4,
      "Version": "*",
      "ActionID": 5031,
      "ActionName": "Filed, by Committee",
      "ActionText": "This Oversight was Filed, by Committee",
      "MatterID": 61827,
      "MatterFile": "T2018-3185",
      "MatterName": "Oversight - Why does the City make it so hard to post bail?",
      "MatterType": "Oversight",
      "MatterStatus": "Filed",
      "LastModified": "2018-12-03T18:11:11.453Z"
    },
    {
      "ID": 343820,
      "GUID": "9F169D13-E486-4649-A0E7-BF3EF93A4C87",
      "Title": "A Local Law to amend the administrative code of the city of New York, in relation to requiring the department of correction to notify incarcerated individuals and their legal representatives when an incarcerated individual is held solely due to a bail amount of less than $10",
      "AgendaSequence": 0,
      "MinutesSequence": 6,
      "Version": "*",
      "ActionID": 17,
      "ActionName": "Laid Over by Committee",
      "ActionText": "This Introduction was Laid Over by Committee",
      "MatterID": 60760,
      "MatterFile": "Int 0944-2018",
      "MatterName": "Requiring the dept of correction to notify inmates, defense attorneys, and court personnel when an inmate is detained solely on a bail amount of one dollar.",
      "MatterType": "Introduction",
      "MatterStatus": "Enacted",
      "LastModified": "2018-12-03T20:07:39.67Z"
    },
    {
      "ID": 343821,
      "GUID": "3BCF3138-9BCF-4796-99AB-A878DEF48023",
      "Title": "A Local Law to amend the administrative code of the city of New York, in relation to removing fees associated with bail payments",
      "AgendaSequence": 0,
      "MinutesSequence": 8,
      "Version": "*",
      "ActionID": 17,
      "ActionName": "Laid Over by Committee",
      "ActionText": "This Introduction was Laid Over by Committee",
      "MatterID": 61583,
      "MatterFile": "Int 1199-2018",
      "MatterName": "Removing fees associated with credit card bail payments and in relation to allowing online bail payment to be made by direct deposit and electronic check.",
      "MatterType": "Introduction",
      "MatterStatus": "Enacted",
      "LastModified": "2018-12-03T20:08:12.79Z"
    }
  ],
  "AgendaLastPublished": "2018-11-27T20:33:23.677Z",
  "MinutesLastPublished": "2019-01-03T15:50:31.75Z",
  "LastModified": "2018-11-27T20:30:35.337Z"
}
