{
  "ID": 77649,
  "GUID": "9C4C2E5E-9DF3-4C52-A20A-CA5BA09AD3E9",
  "File": "Int 0368-2026",
  "Name": "Establishing a tracking system concerning the disposal of yellow and brown grease.",
  "Title": "A Local Law to amend the administrative code of the city of New York, in relation to establishing a tracking system concerning the disposal of yellow and brown grease",
  "TypeID": 2,
  "TypeName": "Introduction",
  "StatusID": 2,
  "StatusName": "Introduced",
  "BodyID": 5108,
  "BodyName": "Committee on Sanitation and Solid Waste Management",
  "IntroDate": "2026-01-29T00:00:00Z",
  "AgendaDate": "2026-01-29T00:00:00Z",
  "PassedDate": "0001-01-01T00:00:00Z",
  "EnactmentDate": "0001-01-01T00:00:00Z",
  "Version": "*",
  "Sponsors": [
    {
      "ID": 7824,
      "Slug": "sandy-nurse",
      "FullName": "Sandy Nurse"
    },
    {
      "ID": 7810,
      "Slug": "amanda-c-farias",
      "FullName": "Amanda C. Farías"
    },
    {
      "ID": 7802,
      "Slug": "erik-d-bottcher",
      "FullName": "Erik D. Bottcher"
    },
    {
      "ID": 7817,
      "Slug": "nantasha-m-williams",
      "FullName": "Nantasha M. Williams"
    },
    {
      "ID": 7823,
      "Slug": "chi-a-osse",
      "FullName": "Chi A. Ossé"
    },
    {
      "ID": 0,
      "Slug": "",
      "FullName": ""
    },
    {
      "ID": 0,
      "Slug": "",
      "FullName": ""
    }
  ],
  "History": [
    {
      "ID": 432525,
      "Date": "2026-01-29T13:25:00Z",
      "ActionID": 27,
      "Action": "Introduced by Council",
      "Description": "This Introduction was Introduced by Council",
      "BodyID": 1,
      "BodyName": "City Council",
      "Version": "*",
      "MatterStatusID": 2,
      "LastModified": "2026-01-29T19:45:23.2Z"
    }
  ],
  "Summary": "",
  "TextID": 81691,
  "LastModified": "2026-02-02T22:26:15.707Z"
}
