{
  "ID": 7538,
  "GUID": "9654056A-29AF-44A2-AFFF-8405FC83E84D",
  "BodyID": 5108,
  "BodyName": "Committee on Sanitation and Solid Waste Management",
  "Date": "2007-09-10T10:30:00-04:00",
  "Location": "Committee Room - City Hall",
  "VideoStatus": "Public",
  "AgendaStatusID": 2,
  "AgendaStatusName": "Final",
  "MinutesStatusID": 2,
  "MinutesStatusName": "Final",
  "AgendaFile": "",
  "InSiteURL": "https://nyc.legistar.com/MeetingDetail.aspx?LEGID=7538&GID=61&G=2FD004F1-D85B-4588-A648-0A736C77D6E3",
  "Items": [
    {
      "ID": 206896,
      "GUID": "FE0BD093-55B5-4BC4-ABE8-688B338EABD1",
      "Title": "A Local Law to amend the administrative code of the city of New York, in relation to limiting the issuance of notices of violations during certain times.",
      "AgendaSequence": 1,
      "MinutesSequence": 3,
      "Version": "*",
      "AgendaNote": "Proposed Int. No. 548-A",
      "MinutesNote": "Proposed Int. No. 548-A",
      "ActionID": 54,
      "ActionName": "Hearing Held by Committee",
      "ActionText": "This Introduction was Hearing Held by Committee",
      "MatterID": 38423,
      "MatterFile": "Int 0548-2007",
      "MatterName": "Limiting the issuance of notices of violations during certain times.",
      "MatterType": "Introduction",
      "MatterStatus": "Enacted",
      "LastModified": "2015-08-25T15:58:59.527Z"
    },
    {
      "ID": 206950,
      "GUID": "C284FE63-04AC-419C-986A-078AC6F66A1C",
      "Title": "Roll Call",
      "AgendaSequence": 0,
      "MinutesSequence": 1,
      "Version": "",
      "RollCallFlag": 1,
      "LastModified": "2015-08-25T15:58:59.527Z"
    },
    {
      "ID": 206951,
      "GUID": "ACE92691-EA44-4E3E-81D8-CD9B71FB6EDA",
      "Title": "A Local Law to amend the administrative code of the city of New York, in relation to limiting the issuance of notices of violations during certain times.",
      "AgendaSequence": 0,
      "MinutesSequence": 4,
      "Version": "*",
      "ActionID": 5001,
      "ActionName": "Amendment Proposed by Comm",
      "ActionText": "This Introduction was Amendment Proposed by Comm",
      "MatterID": 38423,
      "MatterFile": "Int 0548-2007",
      "MatterName": "Limiting the issuance of notices of violations during certain times.",
      "MatterType": "Introduction",
      "MatterStatus": "Enacted",
      "LastModified": "2015-08-25T15:58:59.527Z"
    },
    {
      "ID": 206952,
      "GUID": "83A026FD-4521-4476-8EE0-106C48CD5B08",
      "Title": "A Local Law to amend the administrative code of the city of New York, in relation to limiting the issuance of notices of violations during certain times.",
      "AgendaSequence": 0,
      "MinutesSequence": 5,
      "Version": "*",
      "ActionID": 33,
      "ActionName": "Amended by Committee",
      "ActionText": "This Introduction was Amended by Committee",
      "MatterID": 38423,
      "MatterFile": "Int 0548-2007",
      "MatterName": "Limiting the issuance of notices of violations during certain times.",
      "MatterType": "Introduction",
      "MatterStatus": "Enacted",
      "LastModified": "2015-08-25T15:58:59.527Z"
    },
    {
      "ID": 206953,
      "GUID": "4EB6A146-2B66-4385-B755-0A26680D717F",
      "Title": "A Local Law to amend the administrative code of the city of New York, in relation to limiting the issuance of notices of violations during certain times.",
      "AgendaSequence": 0,
      "MinutesSequence": 6,
      "Version": "A",
      "ActionID": 32,
      "ActionName": "Approved by Committee",
      "ActionText": "A motion was made that this Introduction be Approved by Committee approved by Roll Call.",
      "PassedFlag": 1,
      "PassedFlagName": "Pass",
      "MatterID": 38423,
      "MatterFile": "Int 0548-2007",
      "MatterName": "Limiting the issuance of notices of violations during certain times.",
      "MatterType": "Introduction",
      "MatterStatus": "Enacted",
      "LastModified": "2015-08-25T15:58:59.527Z"
    },
    {
      "ID": 207125,
      "GUID": "034930D0-C28F-43EB-B06C-027CD0499EBB",
      "Title": "",
      "AgendaSequence": 0,
      "MinutesSequence": 2,
      "Version": "",
      "MinutesNote": "Other Council Members Attending: Felder",
      "LastModified": "2015-08-25T15:58:59.527Z"
    }
  ],
  "AgendaLastPublished": "2009-08-10T18:57:13.073Z",
  "MinutesLastPublished": "2009-08-10T19:45:25.09Z",
  "LastModified": "2015-08-25T15:57:12.06Z"
}
